{"WMA": {"interval": ["daily"], "time_period": ["5", "10", "25", "50", "75", "100"], "series_type": ["close"]}, "MAMA": {"interval": ["daily"], "series_type": ["close"], "fast_slow_limit_pair": [[0.1, 0.1], [0.25, 0.25], [0.2, 0.4], [0.4, 0.2], [0.15, 0.3], [0.3, 0.15]]}, "CCI": {"interval": ["daily"], "time_period": ["5", "10", "25", "50", "75", "100"]}, "ROC": {"interval": ["daily"], "time_period": ["5", "10", "25", "50", "75", "100"], "series_type": ["close"]}, "DX": {"interval": ["daily"], "time_period": ["5", "10", "25", "50", "75", "100"]}, "BBANDS": {"interval": ["daily"], "time_period": ["5", "10", "25", "50", "75", "100"], "series_type": ["close"], "nbdevup": ["2.2"], "nbdevdn": ["2.2"], "matype": ["2"]}, "SAR": {"interval": ["daily"], "acceleration and maximum pairs": [[0.01, 0.2], [0.02, 0.2], [0.01, 0.3], [0.02, 0.3]]}, "HT_TRENDLINE": {"interval": ["daily"], "series_type": ["close"]}, "HT_SINE": {"interval": ["daily"], "series_type": ["close"]}, "HT_TRENDMODE": {"interval": ["daily"], "series_type": ["close"]}, "OBV": {"interval": ["daily"]}, "HT_DCPERIOD": {"interval": ["daily"], "series_type": ["close"]}, "HT_DCPHASE": {"interval": ["daily"], "series_type": ["close"]}, "MACD": {"interval": ["daily"], "series_type": ["close"], "fast_period, slow_period, and signal_period pairs": [[12, 26, 9], [26, 52, 9]]}, "APO": {"interval": ["daily"], "series_type": ["close"], "fastperiod, slowperiod pairs": [[5, 10], [10, 20], [20, 40], [8, 20], [10, 34]], "matype": ["2"]}, "PPO": {"interval": ["daily"], "series_type": ["close"], "fastperiod, slowperiod pairs": [[5, 10], [10, 20], [20, 40], [8, 20], [10, 34]], "matype": ["2"]}, "NATR": {"interval": ["daily"], "time_period": ["5", "10", "25", "50", "75", "100"]}}